flake8_force/__init__.py
flake8_force/_version.py
flake8_force-0.0.2.dist-info/LICENSE
flake8_force-0.0.2.dist-info/METADATA
flake8_force-0.0.2.dist-info/WHEEL
flake8_force-0.0.2.dist-info/entry_points.txt
flake8_force-0.0.2.dist-info/top_level.txt
flake8_force-0.0.2.dist-info/RECORD
