Metadata-Version: 2.1
Name: flake8-force
Version: 0.0.2
Summary: flake8 extension to force running check
Home-page: https://github.com/kmaehashi/flake8-force
Author: Kenichi Maehashi
License: MIT
Classifier: Framework :: Flake8
Classifier: License :: OSI Approved :: MIT License
Classifier: Programming Language :: Python
Classifier: Programming Language :: Python :: 3
Classifier: Topic :: Software Development :: Libraries :: Python Modules
Classifier: Topic :: Software Development :: Quality Assurance
License-File: LICENSE
